testdrkv5/__init__.py
testdrkv5/hello.py
testdrkv5-1.0.0.dist-info/METADATA
testdrkv5-1.0.0.dist-info/WHEEL
testdrkv5-1.0.0.dist-info/top_level.txt
testdrkv5-1.0.0.dist-info/RECORD
